src/DetectAge.py
src/__init__.py
local_age_detection_python_backend-0.0.1.dist-info/LICENSE
local_age_detection_python_backend-0.0.1.dist-info/METADATA
local_age_detection_python_backend-0.0.1.dist-info/WHEEL
local_age_detection_python_backend-0.0.1.dist-info/top_level.txt
local_age_detection_python_backend-0.0.1.dist-info/RECORD
