Metadata-Version: 2.1
Name: local-age-detection-python-backend
Version: 0.0.1
Summary: PyPI Package for age detection
Home-page: https://github.com/javatechy/dokr
Author: Circles
Author-email: info@bubbelz.life
Classifier: Programming Language :: Python :: 3
Classifier: License :: Other/Proprietary License
Classifier: Operating System :: OS Independent
License-File: LICENSE
